olsync/__init__.py
olsync/olbrowserlogin.py
olsync/olclient.py
olsync/olsync.py
overleaf_sync-1.2.0.dist-info/entry_points.txt
overleaf_sync-1.2.0.dist-info/LICENSE
overleaf_sync-1.2.0.dist-info/WHEEL
overleaf_sync-1.2.0.dist-info/METADATA
overleaf_sync-1.2.0.dist-info/RECORD
